{"nodes": [{"id": "c_users_ryan_desktop_celestial_website_components_admin_devistable_tsx", "label": "DevisTable.tsx", "file_type": "code", "source_file": "C:\\Users\\Ryan\\Desktop\\Celestial website\\components\\admin\\DevisTable.tsx", "source_location": "L1"}, {"id": "admin_devistable_updatestatut", "label": "updateStatut()", "file_type": "code", "source_file": "C:\\Users\\Ryan\\Desktop\\Celestial website\\components\\admin\\DevisTable.tsx", "source_location": "L31"}, {"id": "admin_devistable_handledelete", "label": "handleDelete()", "file_type": "code", "source_file": "C:\\Users\\Ryan\\Desktop\\Celestial website\\components\\admin\\DevisTable.tsx", "source_location": "L38"}], "edges": [{"source": "c_users_ryan_desktop_celestial_website_components_admin_devistable_tsx", "target": "react", "relation": "imports_from", "context": "import", "confidence": "EXTRACTED", "source_file": "C:\\Users\\Ryan\\Desktop\\Celestial website\\components\\admin\\DevisTable.tsx", "source_location": "L2", "weight": 1.0}, {"source": "c_users_ryan_desktop_celestial_website_components_admin_devistable_tsx", "target": "c_users_ryan_desktop_celestial_website_lib_supabase_client", "relation": "imports_from", "context": "import", "confidence": "EXTRACTED", "source_file": "C:\\Users\\Ryan\\Desktop\\Celestial website\\components\\admin\\DevisTable.tsx", "source_location": "L3", "weight": 1.0}, {"source": "c_users_ryan_desktop_celestial_website_components_admin_devistable_tsx", "target": "supabase_client_createclient", "relation": "imports", "context": "import", "confidence": "EXTRACTED", "source_file": "C:\\Users\\Ryan\\Desktop\\Celestial website\\components\\admin\\DevisTable.tsx", "source_location": "L3", "weight": 1.0}, {"source": "c_users_ryan_desktop_celestial_website_components_admin_devistable_tsx", "target": "navigation", "relation": "imports_from", "context": "import", "confidence": "EXTRACTED", "source_file": "C:\\Users\\Ryan\\Desktop\\Celestial website\\components\\admin\\DevisTable.tsx", "source_location": "L4", "weight": 1.0}, {"source": "c_users_ryan_desktop_celestial_website_components_admin_devistable_tsx", "target": "c_users_ryan_desktop_celestial_website_lib_supabase_types", "relation": "imports_from", "context": "import", "confidence": "EXTRACTED", "source_file": "C:\\Users\\Ryan\\Desktop\\Celestial website\\components\\admin\\DevisTable.tsx", "source_location": "L5", "weight": 1.0}, {"source": "c_users_ryan_desktop_celestial_website_components_admin_devistable_tsx", "target": "supabase_types_database", "relation": "imports", "context": "import", "confidence": "EXTRACTED", "source_file": "C:\\Users\\Ryan\\Desktop\\Celestial website\\components\\admin\\DevisTable.tsx", "source_location": "L5", "weight": 1.0}, {"source": "c_users_ryan_desktop_celestial_website_components_admin_devistable_tsx", "target": "admin_devistable_updatestatut", "relation": "contains", "confidence": "EXTRACTED", "source_file": "C:\\Users\\Ryan\\Desktop\\Celestial website\\components\\admin\\DevisTable.tsx", "source_location": "L31", "weight": 1.0}, {"source": "c_users_ryan_desktop_celestial_website_components_admin_devistable_tsx", "target": "admin_devistable_handledelete", "relation": "contains", "confidence": "EXTRACTED", "source_file": "C:\\Users\\Ryan\\Desktop\\Celestial website\\components\\admin\\DevisTable.tsx", "source_location": "L38", "weight": 1.0}], "raw_calls": [{"caller_nid": "admin_devistable_updatestatut", "callee": "eq", "is_member_call": true, "source_file": "C:\\Users\\Ryan\\Desktop\\Celestial website\\components\\admin\\DevisTable.tsx", "source_location": "L32"}, {"caller_nid": "admin_devistable_updatestatut", "callee": "update", "is_member_call": true, "source_file": "C:\\Users\\Ryan\\Desktop\\Celestial website\\components\\admin\\DevisTable.tsx", "source_location": "L32"}, {"caller_nid": "admin_devistable_updatestatut", "callee": "from", "is_member_call": true, "source_file": "C:\\Users\\Ryan\\Desktop\\Celestial website\\components\\admin\\DevisTable.tsx", "source_location": "L32"}, {"caller_nid": "admin_devistable_updatestatut", "callee": "setData", "is_member_call": false, "source_file": "C:\\Users\\Ryan\\Desktop\\Celestial website\\components\\admin\\DevisTable.tsx", "source_location": "L33"}, {"caller_nid": "admin_devistable_updatestatut", "callee": "setSelected", "is_member_call": false, "source_file": "C:\\Users\\Ryan\\Desktop\\Celestial website\\components\\admin\\DevisTable.tsx", "source_location": "L34"}, {"caller_nid": "admin_devistable_updatestatut", "callee": "refresh", "is_member_call": true, "source_file": "C:\\Users\\Ryan\\Desktop\\Celestial website\\components\\admin\\DevisTable.tsx", "source_location": "L35"}, {"caller_nid": "admin_devistable_handledelete", "callee": "confirm", "is_member_call": false, "source_file": "C:\\Users\\Ryan\\Desktop\\Celestial website\\components\\admin\\DevisTable.tsx", "source_location": "L39"}, {"caller_nid": "admin_devistable_handledelete", "callee": "eq", "is_member_call": true, "source_file": "C:\\Users\\Ryan\\Desktop\\Celestial website\\components\\admin\\DevisTable.tsx", "source_location": "L40"}, {"caller_nid": "admin_devistable_handledelete", "callee": "delete", "is_member_call": true, "source_file": "C:\\Users\\Ryan\\Desktop\\Celestial website\\components\\admin\\DevisTable.tsx", "source_location": "L40"}, {"caller_nid": "admin_devistable_handledelete", "callee": "from", "is_member_call": true, "source_file": "C:\\Users\\Ryan\\Desktop\\Celestial website\\components\\admin\\DevisTable.tsx", "source_location": "L40"}, {"caller_nid": "admin_devistable_handledelete", "callee": "setData", "is_member_call": false, "source_file": "C:\\Users\\Ryan\\Desktop\\Celestial website\\components\\admin\\DevisTable.tsx", "source_location": "L41"}, {"caller_nid": "admin_devistable_handledelete", "callee": "setSelected", "is_member_call": false, "source_file": "C:\\Users\\Ryan\\Desktop\\Celestial website\\components\\admin\\DevisTable.tsx", "source_location": "L42"}, {"caller_nid": "admin_devistable_handledelete", "callee": "refresh", "is_member_call": true, "source_file": "C:\\Users\\Ryan\\Desktop\\Celestial website\\components\\admin\\DevisTable.tsx", "source_location": "L43"}]}